controlm_client/__init__.py
controlm_client/api_client.py
controlm_client/configuration.py
controlm_client/rest.py
controlm_client/api/__init__.py
controlm_client/api/build_api.py
controlm_client/api/config_api.py
controlm_client/api/deploy_api.py
controlm_client/api/provision_api.py
controlm_client/api/reporting_api.py
controlm_client/api/run_api.py
controlm_client/api/samples_api.py
controlm_client/api/session_api.py
controlm_client/models/__init__.py
controlm_client/models/add_agent_params.py
controlm_client/models/add_remote_host_params.py
controlm_client/models/add_remove_success_data.py
controlm_client/models/add_server_params.py
controlm_client/models/agent_details.py
controlm_client/models/agent_details_list.py
controlm_client/models/agent_in_group_params.py
controlm_client/models/agents_in_group_list_result.py
controlm_client/models/agents_in_group_success_data.py
controlm_client/models/allowed_job_actions.py
controlm_client/models/allowed_jobs.py
controlm_client/models/archive_jobs_list.py
controlm_client/models/archive_rules_list.py
controlm_client/models/associate_data.py
controlm_client/models/authentication_data.py
controlm_client/models/client_access_privilege_category.py
controlm_client/models/configuration_manager_privilege_category.py
controlm_client/models/control_m_authentication_data.py
controlm_client/models/ctm_details.py
controlm_client/models/ctm_details_list.py
controlm_client/models/deployment_file_error.py
controlm_client/models/deployment_file_results.py
controlm_client/models/error_data.py
controlm_client/models/error_list.py
controlm_client/models/event.py
controlm_client/models/event_param.py
controlm_client/models/event_set.py
controlm_client/models/external_provider_authentication_data.py
controlm_client/models/folder_auth.py
controlm_client/models/hostgroup_agent_participation.py
controlm_client/models/job.py
controlm_client/models/job_level_auth.py
controlm_client/models/job_run_status.py
controlm_client-9.0.19.dist-info/METADATA
controlm_client-9.0.19.dist-info/WHEEL
controlm_client-9.0.19.dist-info/top_level.txt
controlm_client-9.0.19.dist-info/RECORD
