Metadata-Version: 2.1
Name: controlm-client
Version: 9.0.19
Summary: Control-M Services
Home-page: UNKNOWN
Author: UNKNOWN
Author-email: support@bmc.com
License: UNKNOWN
Keywords: Swagger,Control-M Services
Platform: UNKNOWN
Requires-Dist: certifi (>=2017.4.17)
Requires-Dist: python-dateutil (>=2.1)
Requires-Dist: six (>=1.10)
Requires-Dist: urllib3 (>=1.23)
